fastapi_script/__init__.py
fastapi_script/command.tmpl
fastapi_script/commands.py
fastapi_script/defaults.py
fastapi_script-0.0.8.dist-info/LICENSE
fastapi_script-0.0.8.dist-info/METADATA
fastapi_script-0.0.8.dist-info/WHEEL
fastapi_script-0.0.8.dist-info/top_level.txt
fastapi_script-0.0.8.dist-info/RECORD
