Metadata-Version: 2.1
Name: fastapi-script
Version: 0.0.8
Summary: An extension for FastAPI
Home-page: https://github.com/hitplum/fastapi-script
Author: hitplum
Author-email: ycx921101@163.com
License: MIT
Classifier: Programming Language :: Python :: 3.7
Classifier: Programming Language :: Python :: 3.8
Classifier: Programming Language :: Python :: 3.9
Classifier: Programming Language :: Python :: 3.10
Classifier: Programming Language :: Python :: 3.11
Classifier: Programming Language :: Python :: Implementation :: PyPy
Classifier: License :: OSI Approved :: MIT License
Requires-Python: >=3.7
License-File: LICENSE
Requires-Dist: fastapi
Requires-Dist: uvicorn
